dmba/__init__.py
dmba/data.py
dmba/featureSelection.py
dmba/graphs.py
dmba/metric.py
dmba/textMining.py
dmba/version.py
dmba/csvFiles/Airfares.csv.gz
dmba/csvFiles/Amtrak.csv.gz
dmba/csvFiles/ApplianceShipments.csv.gz
dmba/csvFiles/AustralianWines.csv.gz
dmba/csvFiles/AutoAndElectronics.zip
dmba/csvFiles/Bankruptcy.csv.gz
dmba/csvFiles/BareggTunnel.csv.gz
dmba/csvFiles/BathSoapHousehold.csv.gz
dmba/csvFiles/BostonHousing.csv.gz
dmba/csvFiles/CanadianWorkHours.csv.gz
dmba/csvFiles/CatalogCrossSell.csv.gz
dmba/csvFiles/Cereals.csv.gz
dmba/csvFiles/CharlesBookClub.csv.gz
dmba/csvFiles/Cosmetics.csv.gz
dmba/csvFiles/Coursetopics.csv.gz
dmba/csvFiles/DepartmentStoreSales.csv.gz
dmba/csvFiles/EastWestAirlinesCluster.csv.gz
dmba/csvFiles/EastWestAirlinesNN.csv.gz
dmba/csvFiles/EbayTreemap.csv.gz
dmba/csvFiles/Faceplate.csv.gz
dmba/csvFiles/FlightDelays.csv.gz
dmba/csvFiles/Fundraising.csv.gz
dmba/csvFiles/FutureFundraising.csv.gz
dmba/csvFiles/GermanCredit.csv.gz
dmba/csvFiles/Hair-Care-Product.csv.gz
dmba/csvFiles/LaptopSales.csv.gz
dmba/csvFiles/LaptopSalesJanuary2008.csv.gz
dmba/csvFiles/NYPD_Motor_Vehicle_Collisions_1000.csv.gz
dmba/csvFiles/NaturalGasSales.csv.gz
dmba/csvFiles/Pharmaceuticals.csv.gz
dmba/csvFiles/RidingMowers.csv.gz
dmba/csvFiles/SC-US-students-GPS-data-2016.csv.gz
dmba/csvFiles/SP500.csv.gz
dmba/csvFiles/Sept11Travel.csv.gz
dmba/csvFiles/ShampooSales.csv.gz
dmba/csvFiles/SouvenirSales.csv.gz
dmba/csvFiles/Spambase.csv.gz
dmba/csvFiles/SystemAdministrators.csv.gz
dmba/csvFiles/Taxi-cancellation-case.csv.gz
dmba/csvFiles/Tayko.csv.gz
dmba/csvFiles/TinyData.csv.gz
dmba/csvFiles/ToyotaCorolla.csv.gz
dmba/csvFiles/ToysRUsRevenues.csv.gz
dmba/csvFiles/UniversalBank.csv.gz
dmba/csvFiles/Universities.csv.gz
dmba/csvFiles/Utilities.csv.gz
dmba/csvFiles/Veerhoven.csv.gz
dmba/csvFiles/Voter-Persuasion.csv.gz
dmba/csvFiles/WalMartStock.csv.gz
dmba/csvFiles/WestRoxbury.csv.gz
dmba/csvFiles/Wine.csv.gz
dmba/csvFiles/accidents.csv.gz
dmba-0.2.4.dist-info/LICENSE
dmba-0.2.4.dist-info/METADATA
dmba-0.2.4.dist-info/WHEEL
dmba-0.2.4.dist-info/top_level.txt
dmba-0.2.4.dist-info/RECORD
