Metadata-Version: 2.1
Name: dmba
Version: 0.2.4
Summary: Utility functions for 'Data Mining for Business Analytics: Concepts, Techniques, and Applications in Python'
Home-page: https://github.com/gedeck/dmba
Author: Peter Gedeck
Author-email: mail@petergedeck.com
Classifier: Programming Language :: Python :: 3
Classifier: Programming Language :: Python :: 3.8
Classifier: Programming Language :: Python :: 3.9
Classifier: Programming Language :: Python :: 3.10
Classifier: Programming Language :: Python :: 3.11
Classifier: License :: OSI Approved :: MIT License
Classifier: Operating System :: OS Independent
License-File: LICENSE
Requires-Dist: graphviz
Requires-Dist: matplotlib
Requires-Dist: numpy
Requires-Dist: pandas
Requires-Dist: scikit-learn
Requires-Dist: scipy
Provides-Extra: ipython
Requires-Dist: ipython ; extra == 'ipython'
